Metadata-Version: 2.1
Name: fmskill
Version: 0.8.0
Summary: Compare results from MIKE simulations with observations.
Home-page: https://github.com/DHI/fmskill
Author: Jesper Sandvig Mariegaard
Author-email: jem@dhigroup.com
License: MIT
Classifier: License :: OSI Approved :: MIT License
Classifier: Development Status :: 4 - Beta
Classifier: Intended Audience :: Science/Research
Classifier: Programming Language :: Python
Classifier: Programming Language :: Python :: 3
Classifier: Programming Language :: Python :: 3.8
Classifier: Programming Language :: Python :: 3.9
Classifier: Programming Language :: Python :: 3.10
Classifier: Programming Language :: Python :: 3.11
Classifier: Topic :: Scientific/Engineering
Requires-Python: >=3.8
License-File: LICENSE
Requires-Dist: numpy
Requires-Dist: pandas
Requires-Dist: mikeio (>=1.2)
Requires-Dist: matplotlib
Requires-Dist: xarray
Requires-Dist: markdown
Requires-Dist: jinja2
Provides-Extra: dev
Requires-Dist: pytest ; extra == 'dev'
Requires-Dist: sphinx (==4.5.0) ; extra == 'dev'
Requires-Dist: sphinx-book-theme ; extra == 'dev'
Requires-Dist: black (==22.3.0) ; extra == 'dev'
Requires-Dist: plotly (>=4.5) ; extra == 'dev'
Provides-Extra: notebooks
Requires-Dist: nbformat ; extra == 'notebooks'
Requires-Dist: nbconvert ; extra == 'notebooks'
Requires-Dist: jupyter ; extra == 'notebooks'
Requires-Dist: plotly ; extra == 'notebooks'
Requires-Dist: shapely ; extra == 'notebooks'
Provides-Extra: test
Requires-Dist: pytest ; extra == 'test'
Requires-Dist: netCDF4 ; extra == 'test'
Requires-Dist: openpyxl ; extra == 'test'
Requires-Dist: dask ; extra == 'test'
